{
  "apps/frontend/admin-e2e": {
    "root": [
      "apps/frontend/admin-e2e/project.json",
      "nx/core/project-json"
    ],
    "projectType": [
      "apps/frontend/admin-e2e/project.json",
      "nx/core/project-json"
    ],
    "metadata.targetGroups": [
      "apps/frontend/admin-e2e/cypress.config.ts",
      "@nx/cypress/plugin"
    ],
    "metadata.targetGroups.E2E (CI)": [
      "apps/frontend/admin-e2e/cypress.config.ts",
      "@nx/cypress/plugin"
    ],
    "metadata.targetGroups.E2E (CI).0": [
      "apps/frontend/admin-e2e/cypress.config.ts",
      "@nx/cypress/plugin"
    ],
    "metadata.targetGroups.E2E (CI).1": [
      "apps/frontend/admin-e2e/cypress.config.ts",
      "@nx/cypress/plugin"
    ],
    "targets": [
      "apps/frontend/admin-e2e/cypress.config.ts",
      "@nx/cypress/plugin"
    ],
    "targets.e2e": [
      "apps/frontend/admin-e2e/cypress.config.ts",
      "@nx/cypress/plugin"
    ],
    "targets.e2e.options": [
      "apps/frontend/admin-e2e/cypress.config.ts",
      "@nx/cypress/plugin"
    ],
    "targets.e2e.cache": [
      "apps/frontend/admin-e2e/cypress.config.ts",
      "@nx/cypress/plugin"
    ],
    "targets.e2e.inputs": [
      "apps/frontend/admin-e2e/cypress.config.ts",
      "@nx/cypress/plugin"
    ],
    "targets.e2e.outputs": [
      "apps/frontend/admin-e2e/cypress.config.ts",
      "@nx/cypress/plugin"
    ],
    "targets.e2e.parallelism": [
      "apps/frontend/admin-e2e/cypress.config.ts",
      "@nx/cypress/plugin"
    ],
    "targets.e2e.metadata": [
      "apps/frontend/admin-e2e/cypress.config.ts",
      "@nx/cypress/plugin"
    ],
    "targets.e2e.configurations": [
      "apps/frontend/admin-e2e/cypress.config.ts",
      "@nx/cypress/plugin"
    ],
    "targets.e2e.executor": [
      "apps/frontend/admin-e2e/cypress.config.ts",
      "@nx/cypress/plugin"
    ],
    "targets.e2e.options.cwd": [
      "apps/frontend/admin-e2e/cypress.config.ts",
      "@nx/cypress/plugin"
    ],
    "targets.e2e.options.command": [
      "apps/frontend/admin-e2e/cypress.config.ts",
      "@nx/cypress/plugin"
    ],
    "targets.e2e.configurations.production": [
      "apps/frontend/admin-e2e/cypress.config.ts",
      "@nx/cypress/plugin"
    ],
    "targets.e2e.configurations.production.command": [
      "apps/frontend/admin-e2e/cypress.config.ts",
      "@nx/cypress/plugin"
    ],
    "targets.e2e.metadata.technologies": [
      "apps/frontend/admin-e2e/cypress.config.ts",
      "@nx/cypress/plugin"
    ],
    "targets.e2e.metadata.technologies.0": [
      "apps/frontend/admin-e2e/cypress.config.ts",
      "@nx/cypress/plugin"
    ],
    "targets.e2e.metadata.description": [
      "apps/frontend/admin-e2e/cypress.config.ts",
      "@nx/cypress/plugin"
    ],
    "targets.e2e.metadata.help": [
      "apps/frontend/admin-e2e/cypress.config.ts",
      "@nx/cypress/plugin"
    ],
    "targets.e2e.metadata.help.command": [
      "apps/frontend/admin-e2e/cypress.config.ts",
      "@nx/cypress/plugin"
    ],
    "targets.e2e.metadata.help.example": [
      "apps/frontend/admin-e2e/cypress.config.ts",
      "@nx/cypress/plugin"
    ],
    "targets.e2e-ci--src/e2e/app.cy.ts": [
      "apps/frontend/admin-e2e/cypress.config.ts",
      "@nx/cypress/plugin"
    ],
    "targets.e2e-ci--src/e2e/app.cy.ts.outputs": [
      "apps/frontend/admin-e2e/cypress.config.ts",
      "@nx/cypress/plugin"
    ],
    "targets.e2e-ci--src/e2e/app.cy.ts.inputs": [
      "apps/frontend/admin-e2e/cypress.config.ts",
      "@nx/cypress/plugin"
    ],
    "targets.e2e-ci--src/e2e/app.cy.ts.cache": [
      "apps/frontend/admin-e2e/cypress.config.ts",
      "@nx/cypress/plugin"
    ],
    "targets.e2e-ci--src/e2e/app.cy.ts.options": [
      "apps/frontend/admin-e2e/cypress.config.ts",
      "@nx/cypress/plugin"
    ],
    "targets.e2e-ci--src/e2e/app.cy.ts.parallelism": [
      "apps/frontend/admin-e2e/cypress.config.ts",
      "@nx/cypress/plugin"
    ],
    "targets.e2e-ci--src/e2e/app.cy.ts.metadata": [
      "apps/frontend/admin-e2e/cypress.config.ts",
      "@nx/cypress/plugin"
    ],
    "targets.e2e-ci--src/e2e/app.cy.ts.executor": [
      "apps/frontend/admin-e2e/cypress.config.ts",
      "@nx/cypress/plugin"
    ],
    "targets.e2e-ci--src/e2e/app.cy.ts.options.cwd": [
      "apps/frontend/admin-e2e/cypress.config.ts",
      "@nx/cypress/plugin"
    ],
    "targets.e2e-ci--src/e2e/app.cy.ts.options.command": [
      "apps/frontend/admin-e2e/cypress.config.ts",
      "@nx/cypress/plugin"
    ],
    "targets.e2e-ci--src/e2e/app.cy.ts.metadata.technologies": [
      "apps/frontend/admin-e2e/cypress.config.ts",
      "@nx/cypress/plugin"
    ],
    "targets.e2e-ci--src/e2e/app.cy.ts.metadata.technologies.0": [
      "apps/frontend/admin-e2e/cypress.config.ts",
      "@nx/cypress/plugin"
    ],
    "targets.e2e-ci--src/e2e/app.cy.ts.metadata.description": [
      "apps/frontend/admin-e2e/cypress.config.ts",
      "@nx/cypress/plugin"
    ],
    "targets.e2e-ci--src/e2e/app.cy.ts.metadata.help": [
      "apps/frontend/admin-e2e/cypress.config.ts",
      "@nx/cypress/plugin"
    ],
    "targets.e2e-ci--src/e2e/app.cy.ts.metadata.help.command": [
      "apps/frontend/admin-e2e/cypress.config.ts",
      "@nx/cypress/plugin"
    ],
    "targets.e2e-ci--src/e2e/app.cy.ts.metadata.help.example": [
      "apps/frontend/admin-e2e/cypress.config.ts",
      "@nx/cypress/plugin"
    ],
    "targets.e2e-ci": [
      "apps/frontend/admin-e2e/cypress.config.ts",
      "@nx/cypress/plugin"
    ],
    "targets.e2e-ci.executor": [
      "apps/frontend/admin-e2e/cypress.config.ts",
      "@nx/cypress/plugin"
    ],
    "targets.e2e-ci.cache": [
      "apps/frontend/admin-e2e/cypress.config.ts",
      "@nx/cypress/plugin"
    ],
    "targets.e2e-ci.inputs": [
      "apps/frontend/admin-e2e/cypress.config.ts",
      "@nx/cypress/plugin"
    ],
    "targets.e2e-ci.outputs": [
      "apps/frontend/admin-e2e/cypress.config.ts",
      "@nx/cypress/plugin"
    ],
    "targets.e2e-ci.dependsOn": [
      "apps/frontend/admin-e2e/cypress.config.ts",
      "@nx/cypress/plugin"
    ],
    "targets.e2e-ci.parallelism": [
      "apps/frontend/admin-e2e/cypress.config.ts",
      "@nx/cypress/plugin"
    ],
    "targets.e2e-ci.metadata": [
      "apps/frontend/admin-e2e/cypress.config.ts",
      "@nx/cypress/plugin"
    ],
    "targets.e2e-ci.metadata.technologies": [
      "apps/frontend/admin-e2e/cypress.config.ts",
      "@nx/cypress/plugin"
    ],
    "targets.e2e-ci.metadata.technologies.0": [
      "apps/frontend/admin-e2e/cypress.config.ts",
      "@nx/cypress/plugin"
    ],
    "targets.e2e-ci.metadata.description": [
      "apps/frontend/admin-e2e/cypress.config.ts",
      "@nx/cypress/plugin"
    ],
    "targets.e2e-ci.metadata.nonAtomizedTarget": [
      "apps/frontend/admin-e2e/cypress.config.ts",
      "@nx/cypress/plugin"
    ],
    "targets.e2e-ci.metadata.help": [
      "apps/frontend/admin-e2e/cypress.config.ts",
      "@nx/cypress/plugin"
    ],
    "targets.e2e-ci.metadata.help.command": [
      "apps/frontend/admin-e2e/cypress.config.ts",
      "@nx/cypress/plugin"
    ],
    "targets.e2e-ci.metadata.help.example": [
      "apps/frontend/admin-e2e/cypress.config.ts",
      "@nx/cypress/plugin"
    ],
    "targets.open-cypress": [
      "apps/frontend/admin-e2e/cypress.config.ts",
      "@nx/cypress/plugin"
    ],
    "targets.open-cypress.options": [
      "apps/frontend/admin-e2e/cypress.config.ts",
      "@nx/cypress/plugin"
    ],
    "targets.open-cypress.metadata": [
      "apps/frontend/admin-e2e/cypress.config.ts",
      "@nx/cypress/plugin"
    ],
    "targets.open-cypress.executor": [
      "apps/frontend/admin-e2e/cypress.config.ts",
      "@nx/cypress/plugin"
    ],
    "targets.open-cypress.options.cwd": [
      "apps/frontend/admin-e2e/cypress.config.ts",
      "@nx/cypress/plugin"
    ],
    "targets.open-cypress.options.command": [
      "apps/frontend/admin-e2e/cypress.config.ts",
      "@nx/cypress/plugin"
    ],
    "targets.open-cypress.metadata.technologies": [
      "apps/frontend/admin-e2e/cypress.config.ts",
      "@nx/cypress/plugin"
    ],
    "targets.open-cypress.metadata.technologies.0": [
      "apps/frontend/admin-e2e/cypress.config.ts",
      "@nx/cypress/plugin"
    ],
    "targets.open-cypress.metadata.description": [
      "apps/frontend/admin-e2e/cypress.config.ts",
      "@nx/cypress/plugin"
    ],
    "targets.open-cypress.metadata.help": [
      "apps/frontend/admin-e2e/cypress.config.ts",
      "@nx/cypress/plugin"
    ],
    "targets.open-cypress.metadata.help.command": [
      "apps/frontend/admin-e2e/cypress.config.ts",
      "@nx/cypress/plugin"
    ],
    "targets.open-cypress.metadata.help.example": [
      "apps/frontend/admin-e2e/cypress.config.ts",
      "@nx/cypress/plugin"
    ],
    "targets.lint": [
      "apps/frontend/admin-e2e/eslint.config.mjs",
      "@nx/eslint/plugin"
    ],
    "targets.lint.cache": [
      "apps/frontend/admin-e2e/eslint.config.mjs",
      "@nx/eslint/plugin"
    ],
    "targets.lint.options": [
      "apps/frontend/admin-e2e/eslint.config.mjs",
      "@nx/eslint/plugin"
    ],
    "targets.lint.inputs": [
      "nx.json",
      "nx/target-defaults"
    ],
    "targets.lint.outputs": [
      "apps/frontend/admin-e2e/eslint.config.mjs",
      "@nx/eslint/plugin"
    ],
    "targets.lint.metadata": [
      "apps/frontend/admin-e2e/eslint.config.mjs",
      "@nx/eslint/plugin"
    ],
    "targets.lint.executor": [
      "apps/frontend/admin-e2e/eslint.config.mjs",
      "@nx/eslint/plugin"
    ],
    "targets.lint.options.cwd": [
      "apps/frontend/admin-e2e/eslint.config.mjs",
      "@nx/eslint/plugin"
    ],
    "targets.lint.options.command": [
      "apps/frontend/admin-e2e/eslint.config.mjs",
      "@nx/eslint/plugin"
    ],
    "targets.lint.metadata.technologies": [
      "apps/frontend/admin-e2e/eslint.config.mjs",
      "@nx/eslint/plugin"
    ],
    "targets.lint.metadata.technologies.0": [
      "apps/frontend/admin-e2e/eslint.config.mjs",
      "@nx/eslint/plugin"
    ],
    "targets.lint.metadata.description": [
      "apps/frontend/admin-e2e/eslint.config.mjs",
      "@nx/eslint/plugin"
    ],
    "targets.lint.metadata.help": [
      "apps/frontend/admin-e2e/eslint.config.mjs",
      "@nx/eslint/plugin"
    ],
    "targets.lint.metadata.help.command": [
      "apps/frontend/admin-e2e/eslint.config.mjs",
      "@nx/eslint/plugin"
    ],
    "targets.lint.metadata.help.example": [
      "apps/frontend/admin-e2e/eslint.config.mjs",
      "@nx/eslint/plugin"
    ],
    "name": [
      "apps/frontend/admin-e2e/project.json",
      "nx/core/project-json"
    ],
    "$schema": [
      "apps/frontend/admin-e2e/project.json",
      "nx/core/project-json"
    ],
    "sourceRoot": [
      "apps/frontend/admin-e2e/project.json",
      "nx/core/project-json"
    ],
    "// targets": [
      "apps/frontend/admin-e2e/project.json",
      "nx/core/project-json"
    ],
    "tags": [
      "apps/frontend/admin-e2e/project.json",
      "nx/core/project-json"
    ],
    "implicitDependencies": [
      "apps/frontend/admin-e2e/project.json",
      "nx/core/project-json"
    ],
    "implicitDependencies.admin": [
      "apps/frontend/admin-e2e/project.json",
      "nx/core/project-json"
    ],
    "targets.lint.parallelism": [
      "nx.json",
      "nx/target-defaults"
    ]
  },
  "apps/frontend/customer-e2e": {
    "root": [
      "apps/frontend/customer-e2e/project.json",
      "nx/core/project-json"
    ],
    "projectType": [
      "apps/frontend/customer-e2e/project.json",
      "nx/core/project-json"
    ],
    "metadata.targetGroups": [
      "apps/frontend/customer-e2e/cypress.config.ts",
      "@nx/cypress/plugin"
    ],
    "metadata.targetGroups.E2E (CI)": [
      "apps/frontend/customer-e2e/cypress.config.ts",
      "@nx/cypress/plugin"
    ],
    "metadata.targetGroups.E2E (CI).0": [
      "apps/frontend/customer-e2e/cypress.config.ts",
      "@nx/cypress/plugin"
    ],
    "metadata.targetGroups.E2E (CI).1": [
      "apps/frontend/customer-e2e/cypress.config.ts",
      "@nx/cypress/plugin"
    ],
    "targets": [
      "apps/frontend/customer-e2e/cypress.config.ts",
      "@nx/cypress/plugin"
    ],
    "targets.e2e": [
      "apps/frontend/customer-e2e/cypress.config.ts",
      "@nx/cypress/plugin"
    ],
    "targets.e2e.options": [
      "apps/frontend/customer-e2e/cypress.config.ts",
      "@nx/cypress/plugin"
    ],
    "targets.e2e.cache": [
      "apps/frontend/customer-e2e/cypress.config.ts",
      "@nx/cypress/plugin"
    ],
    "targets.e2e.inputs": [
      "apps/frontend/customer-e2e/cypress.config.ts",
      "@nx/cypress/plugin"
    ],
    "targets.e2e.outputs": [
      "apps/frontend/customer-e2e/cypress.config.ts",
      "@nx/cypress/plugin"
    ],
    "targets.e2e.parallelism": [
      "apps/frontend/customer-e2e/cypress.config.ts",
      "@nx/cypress/plugin"
    ],
    "targets.e2e.metadata": [
      "apps/frontend/customer-e2e/cypress.config.ts",
      "@nx/cypress/plugin"
    ],
    "targets.e2e.configurations": [
      "apps/frontend/customer-e2e/cypress.config.ts",
      "@nx/cypress/plugin"
    ],
    "targets.e2e.executor": [
      "apps/frontend/customer-e2e/cypress.config.ts",
      "@nx/cypress/plugin"
    ],
    "targets.e2e.options.cwd": [
      "apps/frontend/customer-e2e/cypress.config.ts",
      "@nx/cypress/plugin"
    ],
    "targets.e2e.options.command": [
      "apps/frontend/customer-e2e/cypress.config.ts",
      "@nx/cypress/plugin"
    ],
    "targets.e2e.configurations.production": [
      "apps/frontend/customer-e2e/cypress.config.ts",
      "@nx/cypress/plugin"
    ],
    "targets.e2e.configurations.production.command": [
      "apps/frontend/customer-e2e/cypress.config.ts",
      "@nx/cypress/plugin"
    ],
    "targets.e2e.metadata.technologies": [
      "apps/frontend/customer-e2e/cypress.config.ts",
      "@nx/cypress/plugin"
    ],
    "targets.e2e.metadata.technologies.0": [
      "apps/frontend/customer-e2e/cypress.config.ts",
      "@nx/cypress/plugin"
    ],
    "targets.e2e.metadata.description": [
      "apps/frontend/customer-e2e/cypress.config.ts",
      "@nx/cypress/plugin"
    ],
    "targets.e2e.metadata.help": [
      "apps/frontend/customer-e2e/cypress.config.ts",
      "@nx/cypress/plugin"
    ],
    "targets.e2e.metadata.help.command": [
      "apps/frontend/customer-e2e/cypress.config.ts",
      "@nx/cypress/plugin"
    ],
    "targets.e2e.metadata.help.example": [
      "apps/frontend/customer-e2e/cypress.config.ts",
      "@nx/cypress/plugin"
    ],
    "targets.e2e-ci--src/e2e/app.cy.ts": [
      "apps/frontend/customer-e2e/cypress.config.ts",
      "@nx/cypress/plugin"
    ],
    "targets.e2e-ci--src/e2e/app.cy.ts.outputs": [
      "apps/frontend/customer-e2e/cypress.config.ts",
      "@nx/cypress/plugin"
    ],
    "targets.e2e-ci--src/e2e/app.cy.ts.inputs": [
      "apps/frontend/customer-e2e/cypress.config.ts",
      "@nx/cypress/plugin"
    ],
    "targets.e2e-ci--src/e2e/app.cy.ts.cache": [
      "apps/frontend/customer-e2e/cypress.config.ts",
      "@nx/cypress/plugin"
    ],
    "targets.e2e-ci--src/e2e/app.cy.ts.options": [
      "apps/frontend/customer-e2e/cypress.config.ts",
      "@nx/cypress/plugin"
    ],
    "targets.e2e-ci--src/e2e/app.cy.ts.parallelism": [
      "apps/frontend/customer-e2e/cypress.config.ts",
      "@nx/cypress/plugin"
    ],
    "targets.e2e-ci--src/e2e/app.cy.ts.metadata": [
      "apps/frontend/customer-e2e/cypress.config.ts",
      "@nx/cypress/plugin"
    ],
    "targets.e2e-ci--src/e2e/app.cy.ts.executor": [
      "apps/frontend/customer-e2e/cypress.config.ts",
      "@nx/cypress/plugin"
    ],
    "targets.e2e-ci--src/e2e/app.cy.ts.options.cwd": [
      "apps/frontend/customer-e2e/cypress.config.ts",
      "@nx/cypress/plugin"
    ],
    "targets.e2e-ci--src/e2e/app.cy.ts.options.command": [
      "apps/frontend/customer-e2e/cypress.config.ts",
      "@nx/cypress/plugin"
    ],
    "targets.e2e-ci--src/e2e/app.cy.ts.metadata.technologies": [
      "apps/frontend/customer-e2e/cypress.config.ts",
      "@nx/cypress/plugin"
    ],
    "targets.e2e-ci--src/e2e/app.cy.ts.metadata.technologies.0": [
      "apps/frontend/customer-e2e/cypress.config.ts",
      "@nx/cypress/plugin"
    ],
    "targets.e2e-ci--src/e2e/app.cy.ts.metadata.description": [
      "apps/frontend/customer-e2e/cypress.config.ts",
      "@nx/cypress/plugin"
    ],
    "targets.e2e-ci--src/e2e/app.cy.ts.metadata.help": [
      "apps/frontend/customer-e2e/cypress.config.ts",
      "@nx/cypress/plugin"
    ],
    "targets.e2e-ci--src/e2e/app.cy.ts.metadata.help.command": [
      "apps/frontend/customer-e2e/cypress.config.ts",
      "@nx/cypress/plugin"
    ],
    "targets.e2e-ci--src/e2e/app.cy.ts.metadata.help.example": [
      "apps/frontend/customer-e2e/cypress.config.ts",
      "@nx/cypress/plugin"
    ],
    "targets.e2e-ci": [
      "apps/frontend/customer-e2e/cypress.config.ts",
      "@nx/cypress/plugin"
    ],
    "targets.e2e-ci.executor": [
      "apps/frontend/customer-e2e/cypress.config.ts",
      "@nx/cypress/plugin"
    ],
    "targets.e2e-ci.cache": [
      "apps/frontend/customer-e2e/cypress.config.ts",
      "@nx/cypress/plugin"
    ],
    "targets.e2e-ci.inputs": [
      "apps/frontend/customer-e2e/cypress.config.ts",
      "@nx/cypress/plugin"
    ],
    "targets.e2e-ci.outputs": [
      "apps/frontend/customer-e2e/cypress.config.ts",
      "@nx/cypress/plugin"
    ],
    "targets.e2e-ci.dependsOn": [
      "apps/frontend/customer-e2e/cypress.config.ts",
      "@nx/cypress/plugin"
    ],
    "targets.e2e-ci.parallelism": [
      "apps/frontend/customer-e2e/cypress.config.ts",
      "@nx/cypress/plugin"
    ],
    "targets.e2e-ci.metadata": [
      "apps/frontend/customer-e2e/cypress.config.ts",
      "@nx/cypress/plugin"
    ],
    "targets.e2e-ci.metadata.technologies": [
      "apps/frontend/customer-e2e/cypress.config.ts",
      "@nx/cypress/plugin"
    ],
    "targets.e2e-ci.metadata.technologies.0": [
      "apps/frontend/customer-e2e/cypress.config.ts",
      "@nx/cypress/plugin"
    ],
    "targets.e2e-ci.metadata.description": [
      "apps/frontend/customer-e2e/cypress.config.ts",
      "@nx/cypress/plugin"
    ],
    "targets.e2e-ci.metadata.nonAtomizedTarget": [
      "apps/frontend/customer-e2e/cypress.config.ts",
      "@nx/cypress/plugin"
    ],
    "targets.e2e-ci.metadata.help": [
      "apps/frontend/customer-e2e/cypress.config.ts",
      "@nx/cypress/plugin"
    ],
    "targets.e2e-ci.metadata.help.command": [
      "apps/frontend/customer-e2e/cypress.config.ts",
      "@nx/cypress/plugin"
    ],
    "targets.e2e-ci.metadata.help.example": [
      "apps/frontend/customer-e2e/cypress.config.ts",
      "@nx/cypress/plugin"
    ],
    "targets.open-cypress": [
      "apps/frontend/customer-e2e/cypress.config.ts",
      "@nx/cypress/plugin"
    ],
    "targets.open-cypress.options": [
      "apps/frontend/customer-e2e/cypress.config.ts",
      "@nx/cypress/plugin"
    ],
    "targets.open-cypress.metadata": [
      "apps/frontend/customer-e2e/cypress.config.ts",
      "@nx/cypress/plugin"
    ],
    "targets.open-cypress.executor": [
      "apps/frontend/customer-e2e/cypress.config.ts",
      "@nx/cypress/plugin"
    ],
    "targets.open-cypress.options.cwd": [
      "apps/frontend/customer-e2e/cypress.config.ts",
      "@nx/cypress/plugin"
    ],
    "targets.open-cypress.options.command": [
      "apps/frontend/customer-e2e/cypress.config.ts",
      "@nx/cypress/plugin"
    ],
    "targets.open-cypress.metadata.technologies": [
      "apps/frontend/customer-e2e/cypress.config.ts",
      "@nx/cypress/plugin"
    ],
    "targets.open-cypress.metadata.technologies.0": [
      "apps/frontend/customer-e2e/cypress.config.ts",
      "@nx/cypress/plugin"
    ],
    "targets.open-cypress.metadata.description": [
      "apps/frontend/customer-e2e/cypress.config.ts",
      "@nx/cypress/plugin"
    ],
    "targets.open-cypress.metadata.help": [
      "apps/frontend/customer-e2e/cypress.config.ts",
      "@nx/cypress/plugin"
    ],
    "targets.open-cypress.metadata.help.command": [
      "apps/frontend/customer-e2e/cypress.config.ts",
      "@nx/cypress/plugin"
    ],
    "targets.open-cypress.metadata.help.example": [
      "apps/frontend/customer-e2e/cypress.config.ts",
      "@nx/cypress/plugin"
    ],
    "targets.lint": [
      "apps/frontend/customer-e2e/eslint.config.mjs",
      "@nx/eslint/plugin"
    ],
    "targets.lint.cache": [
      "apps/frontend/customer-e2e/eslint.config.mjs",
      "@nx/eslint/plugin"
    ],
    "targets.lint.options": [
      "apps/frontend/customer-e2e/eslint.config.mjs",
      "@nx/eslint/plugin"
    ],
    "targets.lint.inputs": [
      "nx.json",
      "nx/target-defaults"
    ],
    "targets.lint.outputs": [
      "apps/frontend/customer-e2e/eslint.config.mjs",
      "@nx/eslint/plugin"
    ],
    "targets.lint.metadata": [
      "apps/frontend/customer-e2e/eslint.config.mjs",
      "@nx/eslint/plugin"
    ],
    "targets.lint.executor": [
      "apps/frontend/customer-e2e/eslint.config.mjs",
      "@nx/eslint/plugin"
    ],
    "targets.lint.options.cwd": [
      "apps/frontend/customer-e2e/eslint.config.mjs",
      "@nx/eslint/plugin"
    ],
    "targets.lint.options.command": [
      "apps/frontend/customer-e2e/eslint.config.mjs",
      "@nx/eslint/plugin"
    ],
    "targets.lint.metadata.technologies": [
      "apps/frontend/customer-e2e/eslint.config.mjs",
      "@nx/eslint/plugin"
    ],
    "targets.lint.metadata.technologies.0": [
      "apps/frontend/customer-e2e/eslint.config.mjs",
      "@nx/eslint/plugin"
    ],
    "targets.lint.metadata.description": [
      "apps/frontend/customer-e2e/eslint.config.mjs",
      "@nx/eslint/plugin"
    ],
    "targets.lint.metadata.help": [
      "apps/frontend/customer-e2e/eslint.config.mjs",
      "@nx/eslint/plugin"
    ],
    "targets.lint.metadata.help.command": [
      "apps/frontend/customer-e2e/eslint.config.mjs",
      "@nx/eslint/plugin"
    ],
    "targets.lint.metadata.help.example": [
      "apps/frontend/customer-e2e/eslint.config.mjs",
      "@nx/eslint/plugin"
    ],
    "name": [
      "apps/frontend/customer-e2e/project.json",
      "nx/core/project-json"
    ],
    "$schema": [
      "apps/frontend/customer-e2e/project.json",
      "nx/core/project-json"
    ],
    "sourceRoot": [
      "apps/frontend/customer-e2e/project.json",
      "nx/core/project-json"
    ],
    "// targets": [
      "apps/frontend/customer-e2e/project.json",
      "nx/core/project-json"
    ],
    "tags": [
      "apps/frontend/customer-e2e/project.json",
      "nx/core/project-json"
    ],
    "implicitDependencies": [
      "apps/frontend/customer-e2e/project.json",
      "nx/core/project-json"
    ],
    "implicitDependencies.frontend-customer": [
      "apps/frontend/customer-e2e/project.json",
      "nx/core/project-json"
    ],
    "targets.lint.parallelism": [
      "nx.json",
      "nx/target-defaults"
    ]
  },
  "apps/frontend/admin": {
    "root": [
      "apps/frontend/admin/project.json",
      "nx/core/project-json"
    ],
    "targets": [
      "apps/frontend/admin/eslint.config.mjs",
      "@nx/eslint/plugin"
    ],
    "name": [
      "apps/frontend/admin/project.json",
      "nx/core/project-json"
    ],
    "$schema": [
      "apps/frontend/admin/project.json",
      "nx/core/project-json"
    ],
    "projectType": [
      "apps/frontend/admin/project.json",
      "nx/core/project-json"
    ],
    "prefix": [
      "apps/frontend/admin/project.json",
      "nx/core/project-json"
    ],
    "sourceRoot": [
      "apps/frontend/admin/project.json",
      "nx/core/project-json"
    ],
    "tags": [
      "apps/frontend/admin/project.json",
      "nx/core/project-json"
    ],
    "targets.build": [
      "apps/frontend/admin/project.json",
      "nx/core/project-json"
    ],
    "targets.build.executor": [
      "apps/frontend/admin/project.json",
      "nx/core/project-json"
    ],
    "targets.build.outputs": [
      "apps/frontend/admin/project.json",
      "nx/core/project-json"
    ],
    "targets.build.options": [
      "apps/frontend/admin/project.json",
      "nx/core/project-json"
    ],
    "targets.build.configurations": [
      "apps/frontend/admin/project.json",
      "nx/core/project-json"
    ],
    "targets.build.defaultConfiguration": [
      "apps/frontend/admin/project.json",
      "nx/core/project-json"
    ],
    "targets.build.options.outputPath": [
      "apps/frontend/admin/project.json",
      "nx/core/project-json"
    ],
    "targets.build.options.index": [
      "apps/frontend/admin/project.json",
      "nx/core/project-json"
    ],
    "targets.build.options.browser": [
      "apps/frontend/admin/project.json",
      "nx/core/project-json"
    ],
    "targets.build.options.polyfills": [
      "apps/frontend/admin/project.json",
      "nx/core/project-json"
    ],
    "targets.build.options.tsConfig": [
      "apps/frontend/admin/project.json",
      "nx/core/project-json"
    ],
    "targets.build.options.inlineStyleLanguage": [
      "apps/frontend/admin/project.json",
      "nx/core/project-json"
    ],
    "targets.build.options.assets": [
      "apps/frontend/admin/project.json",
      "nx/core/project-json"
    ],
    "targets.build.options.styles": [
      "apps/frontend/admin/project.json",
      "nx/core/project-json"
    ],
    "targets.build.options.scripts": [
      "apps/frontend/admin/project.json",
      "nx/core/project-json"
    ],
    "targets.build.configurations.production": [
      "apps/frontend/admin/project.json",
      "nx/core/project-json"
    ],
    "targets.build.configurations.production.budgets": [
      "apps/frontend/admin/project.json",
      "nx/core/project-json"
    ],
    "targets.build.configurations.production.outputHashing": [
      "apps/frontend/admin/project.json",
      "nx/core/project-json"
    ],
    "targets.build.configurations.development": [
      "apps/frontend/admin/project.json",
      "nx/core/project-json"
    ],
    "targets.build.configurations.development.optimization": [
      "apps/frontend/admin/project.json",
      "nx/core/project-json"
    ],
    "targets.build.configurations.development.extractLicenses": [
      "apps/frontend/admin/project.json",
      "nx/core/project-json"
    ],
    "targets.build.configurations.development.sourceMap": [
      "apps/frontend/admin/project.json",
      "nx/core/project-json"
    ],
    "targets.serve": [
      "apps/frontend/admin/project.json",
      "nx/core/project-json"
    ],
    "targets.serve.executor": [
      "apps/frontend/admin/project.json",
      "nx/core/project-json"
    ],
    "targets.serve.configurations": [
      "apps/frontend/admin/project.json",
      "nx/core/project-json"
    ],
    "targets.serve.defaultConfiguration": [
      "apps/frontend/admin/project.json",
      "nx/core/project-json"
    ],
    "targets.serve.configurations.production": [
      "apps/frontend/admin/project.json",
      "nx/core/project-json"
    ],
    "targets.serve.configurations.production.buildTarget": [
      "apps/frontend/admin/project.json",
      "nx/core/project-json"
    ],
    "targets.serve.configurations.development": [
      "apps/frontend/admin/project.json",
      "nx/core/project-json"
    ],
    "targets.serve.configurations.development.buildTarget": [
      "apps/frontend/admin/project.json",
      "nx/core/project-json"
    ],
    "targets.extract-i18n": [
      "apps/frontend/admin/project.json",
      "nx/core/project-json"
    ],
    "targets.extract-i18n.executor": [
      "apps/frontend/admin/project.json",
      "nx/core/project-json"
    ],
    "targets.extract-i18n.options": [
      "apps/frontend/admin/project.json",
      "nx/core/project-json"
    ],
    "targets.extract-i18n.options.buildTarget": [
      "apps/frontend/admin/project.json",
      "nx/core/project-json"
    ],
    "targets.lint": [
      "apps/frontend/admin/project.json",
      "nx/core/project-json"
    ],
    "targets.lint.executor": [
      "apps/frontend/admin/project.json",
      "nx/core/project-json"
    ],
    "targets.test": [
      "apps/frontend/admin/project.json",
      "nx/core/project-json"
    ],
    "targets.test.executor": [
      "apps/frontend/admin/project.json",
      "nx/core/project-json"
    ],
    "targets.test.outputs": [
      "apps/frontend/admin/project.json",
      "nx/core/project-json"
    ],
    "targets.test.options": [
      "apps/frontend/admin/project.json",
      "nx/core/project-json"
    ],
    "targets.test.options.jestConfig": [
      "apps/frontend/admin/project.json",
      "nx/core/project-json"
    ],
    "targets.serve-static": [
      "apps/frontend/admin/project.json",
      "nx/core/project-json"
    ],
    "targets.serve-static.executor": [
      "apps/frontend/admin/project.json",
      "nx/core/project-json"
    ],
    "targets.serve-static.options": [
      "apps/frontend/admin/project.json",
      "nx/core/project-json"
    ],
    "targets.serve-static.options.buildTarget": [
      "apps/frontend/admin/project.json",
      "nx/core/project-json"
    ],
    "targets.serve-static.options.port": [
      "apps/frontend/admin/project.json",
      "nx/core/project-json"
    ],
    "targets.serve-static.options.staticFilePath": [
      "apps/frontend/admin/project.json",
      "nx/core/project-json"
    ],
    "targets.serve-static.options.spa": [
      "apps/frontend/admin/project.json",
      "nx/core/project-json"
    ],
    "targets.lint.cache": [
      "nx.json",
      "nx/target-defaults"
    ],
    "targets.lint.inputs": [
      "nx.json",
      "nx/target-defaults"
    ],
    "targets.lint.parallelism": [
      "nx.json",
      "nx/target-defaults"
    ],
    "targets.build.cache": [
      "nx.json",
      "nx/target-defaults"
    ],
    "targets.build.dependsOn": [
      "nx.json",
      "nx/target-defaults"
    ],
    "targets.build.inputs": [
      "nx.json",
      "nx/target-defaults"
    ],
    "targets.build.parallelism": [
      "nx.json",
      "nx/target-defaults"
    ],
    "targets.test.cache": [
      "nx.json",
      "nx/target-defaults"
    ],
    "targets.test.inputs": [
      "nx.json",
      "nx/target-defaults"
    ],
    "targets.test.options.passWithNoTests": [
      "nx.json",
      "nx/target-defaults"
    ],
    "targets.test.configurations.ci": [
      "nx.json",
      "nx/target-defaults"
    ],
    "targets.test.configurations.ci.ci": [
      "nx.json",
      "nx/target-defaults"
    ],
    "targets.test.configurations.ci.codeCoverage": [
      "nx.json",
      "nx/target-defaults"
    ],
    "targets.test.parallelism": [
      "nx.json",
      "nx/target-defaults"
    ]
  },
  "apps/frontend/customer": {
    "root": [
      "apps/frontend/customer/project.json",
      "nx/core/project-json"
    ],
    "targets": [
      "apps/frontend/customer/eslint.config.mjs",
      "@nx/eslint/plugin"
    ],
    "name": [
      "apps/frontend/customer/project.json",
      "nx/core/project-json"
    ],
    "$schema": [
      "apps/frontend/customer/project.json",
      "nx/core/project-json"
    ],
    "projectType": [
      "apps/frontend/customer/project.json",
      "nx/core/project-json"
    ],
    "prefix": [
      "apps/frontend/customer/project.json",
      "nx/core/project-json"
    ],
    "sourceRoot": [
      "apps/frontend/customer/project.json",
      "nx/core/project-json"
    ],
    "tags": [
      "apps/frontend/customer/project.json",
      "nx/core/project-json"
    ],
    "targets.build": [
      "apps/frontend/customer/project.json",
      "nx/core/project-json"
    ],
    "targets.build.executor": [
      "apps/frontend/customer/project.json",
      "nx/core/project-json"
    ],
    "targets.build.outputs": [
      "apps/frontend/customer/project.json",
      "nx/core/project-json"
    ],
    "targets.build.options": [
      "apps/frontend/customer/project.json",
      "nx/core/project-json"
    ],
    "targets.build.configurations": [
      "apps/frontend/customer/project.json",
      "nx/core/project-json"
    ],
    "targets.build.defaultConfiguration": [
      "apps/frontend/customer/project.json",
      "nx/core/project-json"
    ],
    "targets.build.options.outputPath": [
      "apps/frontend/customer/project.json",
      "nx/core/project-json"
    ],
    "targets.build.options.index": [
      "apps/frontend/customer/project.json",
      "nx/core/project-json"
    ],
    "targets.build.options.browser": [
      "apps/frontend/customer/project.json",
      "nx/core/project-json"
    ],
    "targets.build.options.polyfills": [
      "apps/frontend/customer/project.json",
      "nx/core/project-json"
    ],
    "targets.build.options.tsConfig": [
      "apps/frontend/customer/project.json",
      "nx/core/project-json"
    ],
    "targets.build.options.inlineStyleLanguage": [
      "apps/frontend/customer/project.json",
      "nx/core/project-json"
    ],
    "targets.build.options.assets": [
      "apps/frontend/customer/project.json",
      "nx/core/project-json"
    ],
    "targets.build.options.styles": [
      "apps/frontend/customer/project.json",
      "nx/core/project-json"
    ],
    "targets.build.options.scripts": [
      "apps/frontend/customer/project.json",
      "nx/core/project-json"
    ],
    "targets.build.configurations.production": [
      "apps/frontend/customer/project.json",
      "nx/core/project-json"
    ],
    "targets.build.configurations.production.budgets": [
      "apps/frontend/customer/project.json",
      "nx/core/project-json"
    ],
    "targets.build.configurations.production.outputHashing": [
      "apps/frontend/customer/project.json",
      "nx/core/project-json"
    ],
    "targets.build.configurations.development": [
      "apps/frontend/customer/project.json",
      "nx/core/project-json"
    ],
    "targets.build.configurations.development.optimization": [
      "apps/frontend/customer/project.json",
      "nx/core/project-json"
    ],
    "targets.build.configurations.development.extractLicenses": [
      "apps/frontend/customer/project.json",
      "nx/core/project-json"
    ],
    "targets.build.configurations.development.sourceMap": [
      "apps/frontend/customer/project.json",
      "nx/core/project-json"
    ],
    "targets.serve": [
      "apps/frontend/customer/project.json",
      "nx/core/project-json"
    ],
    "targets.serve.executor": [
      "apps/frontend/customer/project.json",
      "nx/core/project-json"
    ],
    "targets.serve.configurations": [
      "apps/frontend/customer/project.json",
      "nx/core/project-json"
    ],
    "targets.serve.defaultConfiguration": [
      "apps/frontend/customer/project.json",
      "nx/core/project-json"
    ],
    "targets.serve.configurations.production": [
      "apps/frontend/customer/project.json",
      "nx/core/project-json"
    ],
    "targets.serve.configurations.production.buildTarget": [
      "apps/frontend/customer/project.json",
      "nx/core/project-json"
    ],
    "targets.serve.configurations.development": [
      "apps/frontend/customer/project.json",
      "nx/core/project-json"
    ],
    "targets.serve.configurations.development.buildTarget": [
      "apps/frontend/customer/project.json",
      "nx/core/project-json"
    ],
    "targets.extract-i18n": [
      "apps/frontend/customer/project.json",
      "nx/core/project-json"
    ],
    "targets.extract-i18n.executor": [
      "apps/frontend/customer/project.json",
      "nx/core/project-json"
    ],
    "targets.extract-i18n.options": [
      "apps/frontend/customer/project.json",
      "nx/core/project-json"
    ],
    "targets.extract-i18n.options.buildTarget": [
      "apps/frontend/customer/project.json",
      "nx/core/project-json"
    ],
    "targets.lint": [
      "apps/frontend/customer/project.json",
      "nx/core/project-json"
    ],
    "targets.lint.executor": [
      "apps/frontend/customer/project.json",
      "nx/core/project-json"
    ],
    "targets.test": [
      "apps/frontend/customer/project.json",
      "nx/core/project-json"
    ],
    "targets.test.executor": [
      "apps/frontend/customer/project.json",
      "nx/core/project-json"
    ],
    "targets.test.outputs": [
      "apps/frontend/customer/project.json",
      "nx/core/project-json"
    ],
    "targets.test.options": [
      "apps/frontend/customer/project.json",
      "nx/core/project-json"
    ],
    "targets.test.options.jestConfig": [
      "apps/frontend/customer/project.json",
      "nx/core/project-json"
    ],
    "targets.serve-static": [
      "apps/frontend/customer/project.json",
      "nx/core/project-json"
    ],
    "targets.serve-static.executor": [
      "apps/frontend/customer/project.json",
      "nx/core/project-json"
    ],
    "targets.serve-static.options": [
      "apps/frontend/customer/project.json",
      "nx/core/project-json"
    ],
    "targets.serve-static.options.buildTarget": [
      "apps/frontend/customer/project.json",
      "nx/core/project-json"
    ],
    "targets.serve-static.options.port": [
      "apps/frontend/customer/project.json",
      "nx/core/project-json"
    ],
    "targets.serve-static.options.staticFilePath": [
      "apps/frontend/customer/project.json",
      "nx/core/project-json"
    ],
    "targets.serve-static.options.spa": [
      "apps/frontend/customer/project.json",
      "nx/core/project-json"
    ],
    "targets.lint.cache": [
      "nx.json",
      "nx/target-defaults"
    ],
    "targets.lint.inputs": [
      "nx.json",
      "nx/target-defaults"
    ],
    "targets.lint.parallelism": [
      "nx.json",
      "nx/target-defaults"
    ],
    "targets.build.cache": [
      "nx.json",
      "nx/target-defaults"
    ],
    "targets.build.dependsOn": [
      "nx.json",
      "nx/target-defaults"
    ],
    "targets.build.inputs": [
      "nx.json",
      "nx/target-defaults"
    ],
    "targets.build.parallelism": [
      "nx.json",
      "nx/target-defaults"
    ],
    "targets.test.cache": [
      "nx.json",
      "nx/target-defaults"
    ],
    "targets.test.inputs": [
      "nx.json",
      "nx/target-defaults"
    ],
    "targets.test.options.passWithNoTests": [
      "nx.json",
      "nx/target-defaults"
    ],
    "targets.test.configurations.ci": [
      "nx.json",
      "nx/target-defaults"
    ],
    "targets.test.configurations.ci.ci": [
      "nx.json",
      "nx/target-defaults"
    ],
    "targets.test.configurations.ci.codeCoverage": [
      "nx.json",
      "nx/target-defaults"
    ],
    "targets.test.parallelism": [
      "nx.json",
      "nx/target-defaults"
    ]
  },
  "apps/backend/api": {
    "root": [
      "apps/backend/api/project.json",
      "nx/core/project-json"
    ],
    "targets": [
      "eslint.config.mjs",
      "@nx/eslint/plugin"
    ],
    "targets.lint": [
      "eslint.config.mjs",
      "@nx/eslint/plugin"
    ],
    "targets.lint.cache": [
      "eslint.config.mjs",
      "@nx/eslint/plugin"
    ],
    "targets.lint.options": [
      "eslint.config.mjs",
      "@nx/eslint/plugin"
    ],
    "targets.lint.inputs": [
      "nx.json",
      "nx/target-defaults"
    ],
    "targets.lint.outputs": [
      "eslint.config.mjs",
      "@nx/eslint/plugin"
    ],
    "targets.lint.metadata": [
      "eslint.config.mjs",
      "@nx/eslint/plugin"
    ],
    "targets.lint.executor": [
      "eslint.config.mjs",
      "@nx/eslint/plugin"
    ],
    "targets.lint.options.cwd": [
      "eslint.config.mjs",
      "@nx/eslint/plugin"
    ],
    "targets.lint.options.command": [
      "eslint.config.mjs",
      "@nx/eslint/plugin"
    ],
    "targets.lint.metadata.technologies": [
      "eslint.config.mjs",
      "@nx/eslint/plugin"
    ],
    "targets.lint.metadata.technologies.0": [
      "eslint.config.mjs",
      "@nx/eslint/plugin"
    ],
    "targets.lint.metadata.description": [
      "eslint.config.mjs",
      "@nx/eslint/plugin"
    ],
    "targets.lint.metadata.help": [
      "eslint.config.mjs",
      "@nx/eslint/plugin"
    ],
    "targets.lint.metadata.help.command": [
      "eslint.config.mjs",
      "@nx/eslint/plugin"
    ],
    "targets.lint.metadata.help.example": [
      "eslint.config.mjs",
      "@nx/eslint/plugin"
    ],
    "projectType": [
      "apps/backend/api/project.json",
      "nx/core/project-json"
    ],
    "targets.build": [
      "apps/backend/api/project.json",
      "nx/core/project-json"
    ],
    "targets.build.options": [
      "apps/backend/api/project.json",
      "nx/core/project-json"
    ],
    "targets.build.cache": [
      "apps/backend/api/webpack.config.js",
      "@nx/webpack/plugin"
    ],
    "targets.build.dependsOn": [
      "nx.json",
      "nx/target-defaults"
    ],
    "targets.build.inputs": [
      "nx.json",
      "nx/target-defaults"
    ],
    "targets.build.outputs": [
      "apps/backend/api/webpack.config.js",
      "@nx/webpack/plugin"
    ],
    "targets.build.metadata": [
      "apps/backend/api/webpack.config.js",
      "@nx/webpack/plugin"
    ],
    "targets.build.executor": [
      "apps/backend/api/project.json",
      "nx/core/project-json"
    ],
    "targets.build.options.cwd": [
      "apps/backend/api/webpack.config.js",
      "@nx/webpack/plugin"
    ],
    "targets.build.options.args": [
      "apps/backend/api/project.json",
      "nx/core/project-json"
    ],
    "targets.build.options.command": [
      "apps/backend/api/project.json",
      "nx/core/project-json"
    ],
    "targets.build.metadata.technologies": [
      "apps/backend/api/webpack.config.js",
      "@nx/webpack/plugin"
    ],
    "targets.build.metadata.technologies.0": [
      "apps/backend/api/webpack.config.js",
      "@nx/webpack/plugin"
    ],
    "targets.build.metadata.description": [
      "apps/backend/api/webpack.config.js",
      "@nx/webpack/plugin"
    ],
    "targets.build.metadata.help": [
      "apps/backend/api/webpack.config.js",
      "@nx/webpack/plugin"
    ],
    "targets.build.metadata.help.command": [
      "apps/backend/api/webpack.config.js",
      "@nx/webpack/plugin"
    ],
    "targets.build.metadata.help.example": [
      "apps/backend/api/webpack.config.js",
      "@nx/webpack/plugin"
    ],
    "targets.preview": [
      "apps/backend/api/webpack.config.js",
      "@nx/webpack/plugin"
    ],
    "targets.preview.options": [
      "apps/backend/api/webpack.config.js",
      "@nx/webpack/plugin"
    ],
    "targets.preview.metadata": [
      "apps/backend/api/webpack.config.js",
      "@nx/webpack/plugin"
    ],
    "targets.preview.executor": [
      "apps/backend/api/webpack.config.js",
      "@nx/webpack/plugin"
    ],
    "targets.preview.options.cwd": [
      "apps/backend/api/webpack.config.js",
      "@nx/webpack/plugin"
    ],
    "targets.preview.options.args": [
      "apps/backend/api/webpack.config.js",
      "@nx/webpack/plugin"
    ],
    "targets.preview.options.command": [
      "apps/backend/api/webpack.config.js",
      "@nx/webpack/plugin"
    ],
    "targets.preview.metadata.technologies": [
      "apps/backend/api/webpack.config.js",
      "@nx/webpack/plugin"
    ],
    "targets.preview.metadata.technologies.0": [
      "apps/backend/api/webpack.config.js",
      "@nx/webpack/plugin"
    ],
    "targets.preview.metadata.description": [
      "apps/backend/api/webpack.config.js",
      "@nx/webpack/plugin"
    ],
    "targets.preview.metadata.help": [
      "apps/backend/api/webpack.config.js",
      "@nx/webpack/plugin"
    ],
    "targets.preview.metadata.help.command": [
      "apps/backend/api/webpack.config.js",
      "@nx/webpack/plugin"
    ],
    "targets.preview.metadata.help.example": [
      "apps/backend/api/webpack.config.js",
      "@nx/webpack/plugin"
    ],
    "targets.build-deps": [
      "apps/backend/api/webpack.config.js",
      "@nx/webpack/plugin"
    ],
    "targets.build-deps.dependsOn": [
      "apps/backend/api/webpack.config.js",
      "@nx/webpack/plugin"
    ],
    "targets.watch-deps": [
      "apps/backend/api/webpack.config.js",
      "@nx/webpack/plugin"
    ],
    "targets.watch-deps.dependsOn": [
      "apps/backend/api/webpack.config.js",
      "@nx/webpack/plugin"
    ],
    "targets.watch-deps.executor": [
      "apps/backend/api/webpack.config.js",
      "@nx/webpack/plugin"
    ],
    "targets.watch-deps.options": [
      "apps/backend/api/webpack.config.js",
      "@nx/webpack/plugin"
    ],
    "targets.watch-deps.options.command": [
      "apps/backend/api/webpack.config.js",
      "@nx/webpack/plugin"
    ],
    "name": [
      "apps/backend/api/project.json",
      "nx/core/project-json"
    ],
    "$schema": [
      "apps/backend/api/project.json",
      "nx/core/project-json"
    ],
    "sourceRoot": [
      "apps/backend/api/project.json",
      "nx/core/project-json"
    ],
    "tags": [
      "apps/backend/api/project.json",
      "nx/core/project-json"
    ],
    "targets.build.configurations": [
      "apps/backend/api/project.json",
      "nx/core/project-json"
    ],
    "targets.build.configurations.development": [
      "apps/backend/api/project.json",
      "nx/core/project-json"
    ],
    "targets.build.configurations.development.args": [
      "apps/backend/api/project.json",
      "nx/core/project-json"
    ],
    "targets.serve": [
      "apps/backend/api/project.json",
      "nx/core/project-json"
    ],
    "targets.serve.executor": [
      "apps/backend/api/project.json",
      "nx/core/project-json"
    ],
    "targets.serve.defaultConfiguration": [
      "apps/backend/api/project.json",
      "nx/core/project-json"
    ],
    "targets.serve.dependsOn": [
      "apps/backend/api/project.json",
      "nx/core/project-json"
    ],
    "targets.serve.options": [
      "apps/backend/api/project.json",
      "nx/core/project-json"
    ],
    "targets.serve.configurations": [
      "apps/backend/api/project.json",
      "nx/core/project-json"
    ],
    "targets.serve.options.buildTarget": [
      "apps/backend/api/project.json",
      "nx/core/project-json"
    ],
    "targets.serve.options.runBuildTargetDependencies": [
      "apps/backend/api/project.json",
      "nx/core/project-json"
    ],
    "targets.serve.configurations.development": [
      "apps/backend/api/project.json",
      "nx/core/project-json"
    ],
    "targets.serve.configurations.development.buildTarget": [
      "apps/backend/api/project.json",
      "nx/core/project-json"
    ],
    "targets.serve.configurations.production": [
      "apps/backend/api/project.json",
      "nx/core/project-json"
    ],
    "targets.serve.configurations.production.buildTarget": [
      "apps/backend/api/project.json",
      "nx/core/project-json"
    ],
    "targets.test": [
      "apps/backend/api/project.json",
      "nx/core/project-json"
    ],
    "targets.test.options": [
      "apps/backend/api/project.json",
      "nx/core/project-json"
    ],
    "targets.test.options.passWithNoTests": [
      "apps/backend/api/project.json",
      "nx/core/project-json"
    ],
    "targets.lint.parallelism": [
      "nx.json",
      "nx/target-defaults"
    ],
    "targets.build.parallelism": [
      "nx.json",
      "nx/target-defaults"
    ],
    "targets.test.inputs": [
      "nx.json",
      "nx/target-defaults"
    ],
    "targets.test.parallelism": [
      "nx.json",
      "nx/target-defaults"
    ]
  },
  "apps/backend/api-e2e": {
    "root": [
      "apps/backend/api-e2e/project.json",
      "nx/core/project-json"
    ],
    "targets": [
      "eslint.config.mjs",
      "@nx/eslint/plugin"
    ],
    "targets.lint": [
      "eslint.config.mjs",
      "@nx/eslint/plugin"
    ],
    "targets.lint.cache": [
      "eslint.config.mjs",
      "@nx/eslint/plugin"
    ],
    "targets.lint.options": [
      "eslint.config.mjs",
      "@nx/eslint/plugin"
    ],
    "targets.lint.inputs": [
      "nx.json",
      "nx/target-defaults"
    ],
    "targets.lint.outputs": [
      "eslint.config.mjs",
      "@nx/eslint/plugin"
    ],
    "targets.lint.metadata": [
      "eslint.config.mjs",
      "@nx/eslint/plugin"
    ],
    "targets.lint.executor": [
      "eslint.config.mjs",
      "@nx/eslint/plugin"
    ],
    "targets.lint.options.cwd": [
      "eslint.config.mjs",
      "@nx/eslint/plugin"
    ],
    "targets.lint.options.command": [
      "eslint.config.mjs",
      "@nx/eslint/plugin"
    ],
    "targets.lint.metadata.technologies": [
      "eslint.config.mjs",
      "@nx/eslint/plugin"
    ],
    "targets.lint.metadata.technologies.0": [
      "eslint.config.mjs",
      "@nx/eslint/plugin"
    ],
    "targets.lint.metadata.description": [
      "eslint.config.mjs",
      "@nx/eslint/plugin"
    ],
    "targets.lint.metadata.help": [
      "eslint.config.mjs",
      "@nx/eslint/plugin"
    ],
    "targets.lint.metadata.help.command": [
      "eslint.config.mjs",
      "@nx/eslint/plugin"
    ],
    "targets.lint.metadata.help.example": [
      "eslint.config.mjs",
      "@nx/eslint/plugin"
    ],
    "name": [
      "apps/backend/api-e2e/project.json",
      "nx/core/project-json"
    ],
    "$schema": [
      "apps/backend/api-e2e/project.json",
      "nx/core/project-json"
    ],
    "projectType": [
      "apps/backend/api-e2e/project.json",
      "nx/core/project-json"
    ],
    "implicitDependencies": [
      "apps/backend/api-e2e/project.json",
      "nx/core/project-json"
    ],
    "implicitDependencies.api": [
      "apps/backend/api-e2e/project.json",
      "nx/core/project-json"
    ],
    "targets.e2e": [
      "apps/backend/api-e2e/project.json",
      "nx/core/project-json"
    ],
    "targets.e2e.executor": [
      "apps/backend/api-e2e/project.json",
      "nx/core/project-json"
    ],
    "targets.e2e.outputs": [
      "apps/backend/api-e2e/project.json",
      "nx/core/project-json"
    ],
    "targets.e2e.options": [
      "apps/backend/api-e2e/project.json",
      "nx/core/project-json"
    ],
    "targets.e2e.dependsOn": [
      "apps/backend/api-e2e/project.json",
      "nx/core/project-json"
    ],
    "targets.e2e.options.jestConfig": [
      "apps/backend/api-e2e/project.json",
      "nx/core/project-json"
    ],
    "targets.e2e.options.passWithNoTests": [
      "apps/backend/api-e2e/project.json",
      "nx/core/project-json"
    ],
    "targets.lint.parallelism": [
      "nx.json",
      "nx/target-defaults"
    ],
    "targets.e2e.cache": [
      "nx.json",
      "nx/target-defaults"
    ],
    "targets.e2e.inputs": [
      "nx.json",
      "nx/target-defaults"
    ],
    "targets.e2e.configurations.ci": [
      "nx.json",
      "nx/target-defaults"
    ],
    "targets.e2e.configurations.ci.ci": [
      "nx.json",
      "nx/target-defaults"
    ],
    "targets.e2e.configurations.ci.codeCoverage": [
      "nx.json",
      "nx/target-defaults"
    ],
    "targets.e2e.parallelism": [
      "nx.json",
      "nx/target-defaults"
    ]
  }
}